ticoi/__about__.py
ticoi/__init__.py
ticoi/core.py
ticoi/cube_data_classxr.py
ticoi/cube_writer.py
ticoi/example.py
ticoi/filtering_functions.py
ticoi/interpolation_functions.py
ticoi/inversion_functions.py
ticoi/mjd2date.py
ticoi/optimize_coefficient_functions.py
ticoi/pixel_class.py
ticoi/seasonality_functions.py
ticoi/utils.py
ticoi-0.1.0.dist-info/METADATA
ticoi-0.1.0.dist-info/WHEEL
ticoi-0.1.0.dist-info/licenses/LICENSE
ticoi-0.1.0.dist-info/RECORD
