Metadata-Version: 2.4
Name: ticoi
Version: 0.1.0
Summary: A package to run Temporal Inversion using linear Combinations of Observations, and Interpolation (TICOI)
Project-URL: Homepage, https://github.com/ticoi/ticoi.git
Project-URL: Issues, https://github.com/ticoi/ticoi/issues
Author: Lei Guo
Author-email: Laurane Charrier <laurane.charrier@outlook.com>
License: GPL-3.0-only
License-File: LICENSE
Classifier: Operating System :: OS Independent
Classifier: Programming Language :: Python :: 3
Requires-Python: >=3.10
Requires-Dist: aiohttp
Requires-Dist: dask
Requires-Dist: geopandas
Requires-Dist: h5netcdf
Requires-Dist: jdcal
Requires-Dist: joblib
Requires-Dist: matplotlib
Requires-Dist: notebook
Requires-Dist: numba
Requires-Dist: numpy
Requires-Dist: pandas
Requires-Dist: pyproj
Requires-Dist: rasterio
Requires-Dist: requests
Requires-Dist: rioxarray
Requires-Dist: scikit-learn
Requires-Dist: scipy
Requires-Dist: seaborn
Requires-Dist: shapely
Requires-Dist: statsmodels
Requires-Dist: tqdm
Requires-Dist: xarray
Requires-Dist: zarr
